legaltechtools/__init__.py
legaltechtools/research_tools.py
legaltechtools/scraping_tools.py
legaltechtools-1.0.2.dist-info/LICENSE
legaltechtools-1.0.2.dist-info/METADATA
legaltechtools-1.0.2.dist-info/WHEEL
legaltechtools-1.0.2.dist-info/top_level.txt
legaltechtools-1.0.2.dist-info/RECORD
