Metadata-Version: 2.1
Name: legaltechtools
Version: 1.0.2
Summary: Legal Technology scraping and data analysis library
Home-page: https://github.com/neelkandlikar/legaltechtools
Author: Neel Kandlikar, Neeraj Rattehalli, David Fletcher
Author-email: neelkandlikar@gmail.com
License: MIT
Download-URL: https://pypi.org/project/legaltechtools/
Keywords: LegalTech,LegalTechTools
Platform: UNKNOWN
Requires-Dist: bs4
